[
    {"source": "app\/assistants\/stage-assistant.js"},
    {"source": "lib\/chequelib\/hash.js"},
    {"source": "lib\/syncopate\/storage.js"},
    {
        "scenes": "dashboard",
        "source": "app\/assistants\/dashboard-assistant.js"
    },
    {
        "scenes": "account",
        "source": "app\/assistants\/account-assistant.js"
    },
    {
        "scenes": "dashboard, account",
        "source": "lib\/chequelib\/cheque.js"
    },
    {
        "scenes": "account",
        "source": "lib\/chequelib\/account.js"
    },
    {
        "scenes": "transaction",
        "source": "app\/assistants\/transaction-assistant.js"
    }
]